{
  "title": "Primary school performance tables: 2015",
  "body": "\"The 2015 tables show:   results from the key stage 2 tests in:  reading grammar, punctuation and spelling mathematics   key stage 2 teacher assessments in English, reading, writing, mathematics and science key stage 1 to 2 pupil progress measures in reading, writing and mathematics   Additional school-level data includes:   information on the expenditure of each local-authority-maintained school open for the full 2014 to 2015 financial year the number of teachers, teaching assistants and other school staff the pupil to teacher ratio the mean gross salary of full-time teachers pupil characteristics pupil absences Ofsted ratings    Primary attainment statistics team     Email primary.attainment@education.gov.uk     Telephone: Gemma Coleman 020 7783 8239      \"",
  "base_path": "/government/statistics/primary-school-performance-tables-2015",
  "taxons": [
    {
      "title": "School performance tables and Ofsted reports",
      "base_path": "/education/school-performance-tables-and-ofsted-reports"
    }
  ]
}