{
  "title": "Council Tax Benefit: recipients by passported status and benefit, age and local authority - April 2012",
  "body": "\"Council Tax Benefit statistics published by DWP are based on the Single Housing Benefit Extract (SHBE) data source. This is a monthly electronic scan of claimant level data direct from local authority computer systems.  SHBE has been designed to provide sufficient information for all current and future statistical purposes and is now the single source of Council Tax Benefit data. \"",
  "base_path": "/government/statistics/council-tax-benefit-recipients-by-passported-status-and-benefit-age-and-local-authority-april-2012",
  "taxons": [
    {
      "title": "Community and society",
      "base_path": "/society-and-culture/community-and-society"
    },
    {
      "title": "Equality, rights and citizenship",
      "base_path": "/society-and-culture/equality-rights-and-citizenship"
    },
    {
      "title": "Welfare reform",
      "base_path": "/welfare/welfare-reform"
    }
  ]
}