{
  "title": "Forensic Science Northern Ireland annual report and accounts: 1st April 2006 - 31st March 2007",
  "body": "\"This document contains the following information: Forensic Science Northern Ireland eleventh annual report and accounts: 1st April 2006 - 31st March 2007  FSNI is an executive agency of the Northern Ireland Office  This paper was laid before Parliament in response to a legislative requirement or as a Return to an Address and was ordered to be printed by the House of Commons. \"",
  "base_path": "/government/publications/forensic-science-northern-ireland-annual-report-and-accounts-1st-april-2006-31st-march-2007",
  "taxons": [
    {
      "title": "Science and innovation",
      "base_path": "/business-and-industry/science-and-innovation"
    }
  ]
}